Mung/__init__.py
Mung/frog.py
Mung/House/__init__.py
Mung/House/computer.py
Pjt_Mung-1.2.dist-info/METADATA
Pjt_Mung-1.2.dist-info/WHEEL
Pjt_Mung-1.2.dist-info/top_level.txt
Pjt_Mung-1.2.dist-info/RECORD
