Metadata-Version: 2.1
Name: Pjt-Mung
Version: 1.2
Summary: github-actions push deploy test
Home-page: https://github.com/pjt3591oo/pypi_github_actions_deploy
Author: JeongTae Park
Author-email: pjt3591oo@gmail.com
License: UNKNOWN
Keywords: github,actions,deploy
Platform: UNKNOWN
Classifier: Programming Language :: Python :: 3
Classifier: Programming Language :: Python :: 3.2
Classifier: Programming Language :: Python :: 3.3
Classifier: Programming Language :: Python :: 3.4
Classifier: Programming Language :: Python :: 3.5
Classifier: Programming Language :: Python :: 3.6
Requires-Python: >=3
